ukmon_meteortools/fileformats/UFOAnalyzerXML.py
ukmon_meteortools/fileformats/UFOCapXML.py
ukmon_meteortools/fileformats/__init__.py
ukmon_meteortools/fileformats/ftpDetectInfo.py
ukmon_meteortools/fileformats/imoWorkingShowerList.py
ukmon_meteortools/fileformats/kmlHandlers.py
ukmon_meteortools/fileformats/platepar.py
ukmon_meteortools/rmsutils/__init__.py
ukmon_meteortools/rmsutils/analyseUFOwithRMS.py
ukmon_meteortools/rmsutils/multiDayRadiant.py
ukmon_meteortools/rmsutils/multiEventGroundMap.py
ukmon_meteortools/rmsutils/multiTrackStack.py
ukmon_meteortools/rmsutils/pickleToKml.py
ukmon_meteortools/rmsutils/plotCAMSOrbits.py
ukmon_meteortools/rmsutils/plotRMSOrbits.py
ukmon_meteortools/share/IMO_Working_Meteor_Shower_List.xml
ukmon_meteortools/share/__init__.py
ukmon_meteortools/share/gmn_shower_table_20230518.npy
ukmon_meteortools/share/streamfulldata.npy
ukmon_meteortools/ukmondb/ECSVhandler.py
ukmon_meteortools/ukmondb/__init__.py
ukmon_meteortools/ukmondb/apiExampleCode.py
ukmon_meteortools/ukmondb/getDetections.py
ukmon_meteortools/ukmondb/getLiveImages.py
ukmon_meteortools/ukmondb/trajPickle.py
ukmon_meteortools/ukmondb/trajectoryKML.py
ukmon_meteortools/utils/Math.py
ukmon_meteortools/utils/VectorMaths.py
ukmon_meteortools/utils/__init__.py
ukmon_meteortools/utils/annotateImage.py
ukmon_meteortools/utils/convertSolLon.py
ukmon_meteortools/utils/drawFTPfile.py
ukmon_meteortools/utils/findNearDuplicates.py
ukmon_meteortools/utils/getActiveShowers.py
ukmon_meteortools/utils/getOverlappingFovs.py
ukmon_meteortools/utils/getRiseSet.py
ukmon_meteortools/utils/getShowerDates.py
ukmon_meteortools/utils/plotTrack.py
ukmon_meteortools/utils/sendAnEmail.py
ukmon_meteortools-2023.7.10.dist-info/LICENSE
ukmon_meteortools-2023.7.10.dist-info/METADATA
ukmon_meteortools-2023.7.10.dist-info/WHEEL
ukmon_meteortools-2023.7.10.dist-info/top_level.txt
ukmon_meteortools-2023.7.10.dist-info/RECORD
